shachange/__init__.py
shachange/__main__.py
shachange/shachange.py
shachange-1.2.dist-info/DESCRIPTION.rst
shachange-1.2.dist-info/METADATA
shachange-1.2.dist-info/RECORD
shachange-1.2.dist-info/WHEEL
shachange-1.2.dist-info/entry_points.txt
shachange-1.2.dist-info/metadata.json
shachange-1.2.dist-info/top_level.txt
